{"cameraMode":{"drawMode":0,"name":"Shaded","section":"Shading Mode"},"sceneLighting":false,"audioPlay":false,"sceneViewState":{"m_AlwaysRefresh":false,"showFog":true,"showSkybox":false,"showFlares":true,"showImageEffects":true,"showParticleSystems":true,"showVisualEffectGraphs":true,"m_FxEnabled":true},"in2DMode":false,"pivot":{"x":45.83099365234375,"y":9.458707809448243,"z":-2.282560348510742},"rotation":{"x":-0.26896971464157107,"y":-0.3334353268146515,"z":0.0998663380742073,"w":-0.8980587720870972},"size":10.036630630493164,"orthographic":false}